foreign_fields/__init__.py
foreign_fields/fields.py
foreign_fields/test_forms.py
foreign_fields/test_models.py
foreign_fields/tests.py
foreign_fields/migrations/0001_initial.py
foreign_fields/migrations/__init__.py
django_foreign_fields-0.3.2.dist-info/LICENSE
django_foreign_fields-0.3.2.dist-info/METADATA
django_foreign_fields-0.3.2.dist-info/WHEEL
django_foreign_fields-0.3.2.dist-info/top_level.txt
django_foreign_fields-0.3.2.dist-info/RECORD
