Metadata-Version: 2.1
Name: django-foreign-fields
Version: 0.3.2
Summary: A Django app with new form fields for handling foreign relationships.
Home-page: https://github.com/ThiagoCTN/django-foreign-fields/
Author: Thiago Nascimento
Author-email: thiagocampostn@gmail.com
License: MIT License
Classifier: Environment :: Web Environment
Classifier: Framework :: Django
Classifier: Intended Audience :: Developers
Classifier: License :: OSI Approved :: MIT License
Classifier: Operating System :: OS Independent
Classifier: Programming Language :: Python
Classifier: Programming Language :: Python :: 3.5
Classifier: Programming Language :: Python :: 3.6
Classifier: Topic :: Internet :: WWW/HTTP
Classifier: Topic :: Internet :: WWW/HTTP :: Dynamic Content
License-File: LICENSE
